bwskel/__init__.py
bwskel/bwskel.py
bwskel/helpers.py
bwskel/prune_edges3.py
bwskel_3d-0.1.3.dist-info/METADATA
bwskel_3d-0.1.3.dist-info/WHEEL
bwskel_3d-0.1.3.dist-info/top_level.txt
bwskel_3d-0.1.3.dist-info/RECORD
