Metadata-Version: 2.4
Name: bwskel_3d
Version: 0.1.3
Summary: 3D binary skeletonization and pruning, Python replication of MATLAB bwskel
Home-page: https://github.com/dujay971226/bwskel
Author: Yunze Du
Classifier: Programming Language :: Python :: 3
Classifier: Operating System :: OS Independent
Requires-Python: >=3.7
Requires-Dist: numpy
Requires-Dist: scipy
Requires-Dist: scikit-image
Dynamic: author
Dynamic: classifier
Dynamic: home-page
Dynamic: requires-dist
Dynamic: requires-python
Dynamic: summary
